LICENSE
README.md
polars_u256_plugin-0.2.2.dist-info/METADATA
polars_u256_plugin-0.2.2.dist-info/WHEEL
polars_u256_plugin-0.2.2.dist-info/licenses/LICENSE
polars_u256_plugin/__init__.py
polars_u256_plugin/_internal.abi3.so
polars_u256_plugin/display.py
polars_u256_plugin/expr_namespace.py
polars_u256_plugin/py.typed
polars_u256_plugin-0.2.2.dist-info/RECORD
