Metadata-Version: 2.4
Name: polars_u256_plugin
Version: 0.2.2
Classifier: Programming Language :: Python :: 3
Classifier: Programming Language :: Rust
Classifier: License :: OSI Approved :: MIT License
Classifier: Operating System :: OS Independent
Requires-Dist: polars>=1.3.0
Requires-Dist: pytest>=6.0 ; extra == 'dev'
Provides-Extra: dev
License-File: LICENSE
Summary: Polars plugin for 256-bit U256 and signed I256 (two's complement) integers backed by ruint
Author: polars-u256-plugin authors
License: MIT
Requires-Python: >=3.9
Project-URL: Homepage, https://pypi.org/project/polars_u256_plugin/
Project-URL: Repository, https://github.com/elyase/polars-u256-plugin
Project-URL: Issues, https://github.com/elyase/polars-u256-plugin/issues
